{"metadata": {"dbt_schema_version": "https://schemas.getdbt.com/dbt/run-results/v4.json", "dbt_version": "1.0.4", "generated_at": "2022-04-14T03:19:11.598839Z", "invocation_id": "fc6cdb46-f685-45b2-ab53-3e0aaaba3194", "env": {}}, "results": [{"status": "success", "timing": [{"name": "compile", "started_at": "2022-04-14T03:19:11.547949Z", "completed_at": "2022-04-14T03:19:11.562469Z"}, {"name": "execute", "started_at": "2022-04-14T03:19:11.562983Z", "completed_at": "2022-04-14T03:19:11.562983Z"}], "thread_id": "Thread-5", "execution_time": 0.01643085479736328, "adapter_response": {}, "message": null, "failures": null, "unique_id": "seed.firstdbtproject.seed_full_moon_dates"}, {"status": "success", "timing": [{"name": "compile", "started_at": "2022-04-14T03:19:11.547949Z", "completed_at": "2022-04-14T03:19:11.547949Z"}, {"name": "execute", "started_at": "2022-04-14T03:19:11.564380Z", "completed_at": "2022-04-14T03:19:11.564380Z"}], "thread_id": "Thread-1", "execution_time": 0.01643085479736328, "adapter_response": {}, "message": null, "failures": null, "unique_id": "model.firstdbtproject.customerpayments"}, {"status": "success", "timing": [{"name": "compile", "started_at": "2022-04-14T03:19:11.547949Z", "completed_at": "2022-04-14T03:19:11.563885Z"}, {"name": "execute", "started_at": "2022-04-14T03:19:11.564380Z", "completed_at": "2022-04-14T03:19:11.564380Z"}], "thread_id": "Thread-3", "execution_time": 0.01643085479736328, "adapter_response": {}, "message": null, "failures": null, "unique_id": "model.firstdbtproject.src_employees"}, {"status": "success", "timing": [{"name": "compile", "started_at": "2022-04-14T03:19:11.547949Z", "completed_at": "2022-04-14T03:19:11.564380Z"}, {"name": "execute", "started_at": "2022-04-14T03:19:11.564380Z", "completed_at": "2022-04-14T03:19:11.564380Z"}], "thread_id": "Thread-4", "execution_time": 0.01643085479736328, "adapter_response": {}, "message": null, "failures": null, "unique_id": "model.firstdbtproject.testingmodel"}, {"status": "success", "timing": [{"name": "compile", "started_at": "2022-04-14T03:19:11.547949Z", "completed_at": "2022-04-14T03:19:11.564380Z"}, {"name": "execute", "started_at": "2022-04-14T03:19:11.564380Z", "completed_at": "2022-04-14T03:19:11.564380Z"}], "thread_id": "Thread-2", "execution_time": 0.01643085479736328, "adapter_response": {}, "message": null, "failures": null, "unique_id": "model.firstdbtproject.my_first_dbt_model"}, {"status": "success", "timing": [{"name": "compile", "started_at": "2022-04-14T03:19:11.564380Z", "completed_at": "2022-04-14T03:19:11.580448Z"}, {"name": "execute", "started_at": "2022-04-14T03:19:11.585882Z", "completed_at": "2022-04-14T03:19:11.585882Z"}], "thread_id": "Thread-7", "execution_time": 0.021502017974853516, "adapter_response": {}, "message": null, "failures": null, "unique_id": "model.firstdbtproject.my_second_dbt_model"}, {"status": "success", "timing": [{"name": "compile", "started_at": "2022-04-14T03:19:11.564380Z", "completed_at": "2022-04-14T03:19:11.586368Z"}, {"name": "execute", "started_at": "2022-04-14T03:19:11.586818Z", "completed_at": "2022-04-14T03:19:11.586818Z"}], "thread_id": "Thread-8", "execution_time": 0.022437572479248047, "adapter_response": {}, "message": null, "failures": null, "unique_id": "test.firstdbtproject.not_null_my_first_dbt_model_id.5fb22c2710"}, {"status": "success", "timing": [{"name": "compile", "started_at": "2022-04-14T03:19:11.564380Z", "completed_at": "2022-04-14T03:19:11.586818Z"}, {"name": "execute", "started_at": "2022-04-14T03:19:11.586818Z", "completed_at": "2022-04-14T03:19:11.586818Z"}], "thread_id": "Thread-9", "execution_time": 0.022437572479248047, "adapter_response": {}, "message": null, "failures": null, "unique_id": "test.firstdbtproject.unique_my_first_dbt_model_id.16e066b321"}, {"status": "success", "timing": [{"name": "compile", "started_at": "2022-04-14T03:19:11.586818Z", "completed_at": "2022-04-14T03:19:11.586818Z"}, {"name": "execute", "started_at": "2022-04-14T03:19:11.586818Z", "completed_at": "2022-04-14T03:19:11.586818Z"}], "thread_id": "Thread-5", "execution_time": 0.0, "adapter_response": {}, "message": null, "failures": null, "unique_id": "test.firstdbtproject.unique_my_second_dbt_model_id.57a0f8c493"}, {"status": "success", "timing": [{"name": "compile", "started_at": "2022-04-14T03:19:11.586818Z", "completed_at": "2022-04-14T03:19:11.586818Z"}, {"name": "execute", "started_at": "2022-04-14T03:19:11.586818Z", "completed_at": "2022-04-14T03:19:11.586818Z"}], "thread_id": "Thread-6", "execution_time": 0.0, "adapter_response": {}, "message": null, "failures": null, "unique_id": "test.firstdbtproject.not_null_my_second_dbt_model_id.151b76d778"}], "elapsed_time": 2.28332781791687, "args": {"write_json": true, "use_colors": true, "printer_width": 80, "version_check": true, "partial_parse": true, "static_parser": true, "profiles_dir": "C:\\Users\\manid\\.dbt", "send_anonymous_usage_stats": true, "event_buffer_size": 100000, "compile": true, "which": "generate", "rpc_method": "docs.generate", "indirect_selection": "eager"}}